intstreamsdk/__init__.py
intstreamsdk/client.py
intstreamsdk/extract.py
intstreamsdk/job.py
intstreamsdk/mitigate.py
intstreamsdk/resource.py
tests/__init__.py
tests/integration.py
intstreamsdk-1.0.20.dist-info/METADATA
intstreamsdk-1.0.20.dist-info/WHEEL
intstreamsdk-1.0.20.dist-info/top_level.txt
intstreamsdk-1.0.20.dist-info/RECORD
