Metadata-Version: 2.1
Name: intstreamsdk
Version: 1.0.20
Summary: Instream job script
Home-page: https://todo
Author: Aaron Jonen
Author-email: aaron.jonen@cypherint.com
License: UNKNOWN
Keywords: development intstream
Platform: UNKNOWN
Classifier: Development Status :: 3 - Alpha
Classifier: Intended Audience :: Developers
Classifier: Topic :: Software Development :: Build Tools
Classifier: License :: OSI Approved :: MIT License
Classifier: Programming Language :: Python :: 3.6
Requires-Python: >=3.6, <4
Requires-Dist: iocextract
Requires-Dist: tldextract
Requires-Dist: requests
Requires-Dist: requests-futures
Provides-Extra: dev
Provides-Extra: test
